backups/__init__.py
backups/actions.py
backups/admin.py
backups/apps.py
backups/models.py
backups/tasks.py
backups/tests.py
backups/urls.py
backups/utils.py
backups/views.py
backups/migrations/0001_initial.py
backups/migrations/__init__.py
django_backups-0.0.2.dist-info/LICENSE
django_backups-0.0.2.dist-info/METADATA
django_backups-0.0.2.dist-info/WHEEL
django_backups-0.0.2.dist-info/top_level.txt
django_backups-0.0.2.dist-info/RECORD
