Metadata-Version: 2.1
Name: django-backups
Version: 0.0.2
Summary: Django package for backing up databases.
Classifier: Programming Language :: Python :: 3
Classifier: License :: OSI Approved :: MIT License
Classifier: Operating System :: OS Independent
Requires-Python: >=3.8
License-File: LICENSE
Requires-Dist: Django
Requires-Dist: boto3
Requires-Dist: celery
Requires-Dist: psycopg2
Requires-Dist: python-dotenv
Requires-Dist: amqp
Requires-Dist: asgiref
Requires-Dist: billiard
Requires-Dist: botocore
Requires-Dist: click
Requires-Dist: click-didyoumean
Requires-Dist: click-plugins
Requires-Dist: click-repl
Requires-Dist: jmespath
Requires-Dist: kombu
Requires-Dist: prompt-toolkit
Requires-Dist: python-dateutil
Requires-Dist: s3transfer
Requires-Dist: six
Requires-Dist: sqlparse
Requires-Dist: tzdata
Requires-Dist: urllib3
Requires-Dist: vine
Requires-Dist: wcwidth
